ginza_transformers/__init__.py
ginza_transformers/pipeline_component.py
ginza_transformers/setup_model.py
ginza_transformers/layers/__init__.py
ginza_transformers/layers/hf_shim_custom.py
ginza_transformers/layers/transformer_model.py
ginza_transformers-0.4.2.dist-info/LICENSE
ginza_transformers-0.4.2.dist-info/METADATA
ginza_transformers-0.4.2.dist-info/WHEEL
ginza_transformers-0.4.2.dist-info/entry_points.txt
ginza_transformers-0.4.2.dist-info/top_level.txt
ginza_transformers-0.4.2.dist-info/RECORD
