Metadata-Version: 2.1
Name: ginza-transformers
Version: 0.4.2
Summary: ginza-transformers
Home-page: https://github.com/megagonlabs/ginza-transformers
Author: Megagon Labs, Tokyo.
Author-email: ginza@megagon.ai
License: MIT
Platform: UNKNOWN
License-File: LICENSE
Requires-Dist: spacy-transformers (<1.2.0,>=1.1.2)
